cloudmesh_gitissues/GitPriority.py
cloudmesh_gitissues/__init__.py
cloudmesh_gitissues/settings.py
cloudmesh_gitissues/urls.py
cloudmesh_gitissues/version.py
cloudmesh_gitissues/views.py
cloudmesh_gitissues/wsgi.py
cloudmesh_gitissues/issues/__init__.py
cloudmesh_gitissues/issues/views.py
cloudmesh_gitissues-3.1.2.dist-info/DESCRIPTION.rst
cloudmesh_gitissues-3.1.2.dist-info/METADATA
cloudmesh_gitissues-3.1.2.dist-info/RECORD
cloudmesh_gitissues-3.1.2.dist-info/WHEEL
cloudmesh_gitissues-3.1.2.dist-info/metadata.json
cloudmesh_gitissues-3.1.2.dist-info/top_level.txt
