Metadata-Version: 2.0
Name: cloudmesh-gitissues
Version: 3.1.2
Summary: cloudmesh_gitissues - Manageing Issue Priorities in github
Home-page: https://github.com/cloudmesh/gitissues
Author: Gregor von Laszewski
Author-email: laszewski@gmail.com
License: Apache License, Version 2.0
Keywords: cloud cmd commandshell plugins
Platform: UNKNOWN
Classifier: Intended Audience :: Developers
Classifier: Intended Audience :: Education
Classifier: Intended Audience :: Science/Research
Classifier: Development Status :: 2 - Pre-Alpha
Classifier: Intended Audience :: Developers
Classifier: License :: OSI Approved :: Apache Software License
Classifier: Operating System :: MacOS :: MacOS X
Classifier: Operating System :: POSIX :: Linux
Classifier: Programming Language :: Python :: 2.7
Classifier: Programming Language :: Python :: 3.5
Classifier: Framework :: Django
Classifier: Topic :: Software Development
Classifier: Topic :: Software Development :: User Interfaces
Classifier: Topic :: Software Development :: Version Control
Classifier: Topic :: Software Development :: Libraries :: Python Modules
Classifier: Topic :: Utilities
Requires-Dist: aldjemy
Requires-Dist: cloudmesh-client
Requires-Dist: cloudmesh-workflow
Requires-Dist: django-admin-bootstrapped
Requires-Dist: django-bootstrap-themes
Requires-Dist: django-bootstrap3
Requires-Dist: django-filter
Requires-Dist: django-jinja
Requires-Dist: django-jinja-bootstrap-form
Requires-Dist: django-rest-swagger
Requires-Dist: djangorestframework
Requires-Dist: jinja2schema
Requires-Dist: markdown
Requires-Dist: nwdiag
Requires-Dist: pygal
